{
    "name": "Drum",
    "wam3d": {"aspect_ratio":1,"size":0.7,"bottom_color":"#ffffff","top_color":"#aaaaaa","face":"leather","face_color":"#ffffff","outline_color":"#663c3c","outline_width":0.04,"shape":"circle","modifier":"normal","modifier_strength":0.6,"controls":[{"x":0,"y":0.4241048750536654,"width":0.1497991967871486,"height":0.14176706827309246,"values":{"Color":"#33BB88"},"control":"midi_input_control"},{"x":0.8502008032128514,"y":0.4241048750536654,"width":0.1497991967871486,"height":0.1517902498926692,"values":{"Color":"#FF0000"},"control":"output_control"},{"x":0.4501963428765049,"y":0,"width":0.5240597740422341,"height":0.51765064923558,"values":{"Shape/Shape":"circle","Shape/Top Color":"#f1f138","Shape/Bottom Color":"#e6c56f","Shape/Outline Color":"#000000","Shape/Outline Width":0,"Shape/Front Face Image":"iron","Shape/Front Face Color":"#eebb33","Shape/Modifier":"normal","Shape/Modifier Strength":0.5,"Shape/Height":0.1,"Shape/Rotation":0},"control":"decoration"},{"x":0.2538316052512879,"y":0.3662612984695675,"width":0.05000000000000002,"height":0.5626487256540834,"values":{"Shape/Shape":"rectangle","Shape/Top Color":"#d0832d","Shape/Bottom Color":"#987043","Shape/Outline Color":"#000000","Shape/Outline Width":0,"Shape/Front Face Image":"","Shape/Front Face Color":"#FFFFFF","Shape/Modifier":"down_wide","Shape/Modifier Strength":0.75,"Shape/Height":1,"Shape/Rotation":0},"control":"decoration"},{"x":0.344533261046375,"y":0.4228941790193663,"width":0.050000000000000044,"height":0.5771058209806336,"values":{"Shape/Shape":"rectangle","Shape/Top Color":"#d0832d","Shape/Bottom Color":"#987043","Shape/Outline Color":"#000000","Shape/Outline Width":0,"Shape/Front Face Image":"","Shape/Front Face Color":"#FFFFFF","Shape/Modifier":"down_wide","Shape/Modifier Strength":0.66,"Shape/Height":0.991,"Shape/Rotation":0},"control":"decoration"},{"x":0.52976498730213,"y":0.51765064923558,"width":0.19070165579508702,"height":0.2024011490427201,"values":{"Text":"Drum","Color":"#e6e8a6","Outline Color":"#c77b4e","Outline Width":0.055,"Font":"bedstead"},"control":"text"}],"wam_url":"https://editor.sequencer.party/plugins/burns-audio/drumsampler/index.js"}
}